{"stats":{"minecraft:picked_up":{"minecraft:carved_pumpkin":1},"minecraft:custom":{"minecraft:jump":172,"minecraft:time_since_rest":14986,"minecraft:crouch_one_cm":534,"minecraft:damage_dealt":250,"minecraft:damage_taken":570,"minecraft:play_time":15310,"minecraft:leave_game":3,"minecraft:sprint_one_cm":44317,"minecraft:walk_one_cm":11253,"minecraft:time_since_death":14954,"minecraft:deaths":2,"minecraft:sneak_time":121,"minecraft:total_world_time":15310,"minecraft:interact_with_crafting_table":1,"minecraft:fall_one_cm":31194,"minecraft:fly_one_cm":36308}},"DataVersion":3465}